odoo/addons/partner_email_check/README.rst
odoo/addons/partner_email_check/__init__.py
odoo/addons/partner_email_check/__manifest__.py
odoo/addons/partner_email_check/demo/res_company_demo.xml
odoo/addons/partner_email_check/i18n/es.po
odoo/addons/partner_email_check/i18n/fr.po
odoo/addons/partner_email_check/i18n/it.po
odoo/addons/partner_email_check/i18n/partner_email_check.pot
odoo/addons/partner_email_check/models/__init__.py
odoo/addons/partner_email_check/models/res_company.py
odoo/addons/partner_email_check/models/res_config_settings.py
odoo/addons/partner_email_check/models/res_partner.py
odoo/addons/partner_email_check/readme/CONFIGURE.md
odoo/addons/partner_email_check/readme/CONTRIBUTORS.md
odoo/addons/partner_email_check/readme/CREDITS.md
odoo/addons/partner_email_check/readme/DESCRIPTION.md
odoo/addons/partner_email_check/readme/USAGE.md
odoo/addons/partner_email_check/static/description/icon.png
odoo/addons/partner_email_check/static/description/index.html
odoo/addons/partner_email_check/tests/__init__.py
odoo/addons/partner_email_check/tests/test_partner_email_check.py
odoo/addons/partner_email_check/views/base_config_view.xml
odoo_addon_partner_email_check-18.0.1.0.0.2.dist-info/METADATA
odoo_addon_partner_email_check-18.0.1.0.0.2.dist-info/WHEEL
odoo_addon_partner_email_check-18.0.1.0.0.2.dist-info/top_level.txt
odoo_addon_partner_email_check-18.0.1.0.0.2.dist-info/RECORD
